swcolorpicker/__init__.py
swcolorpicker/__main__.py
swcolorpicker/img.py
swcolorpicker/swcolorpicker.py
swcolorpicker/ui_dark.py
swcolorpicker/ui_dark_alpha.py
swcolorpicker-1.4.3.dist-info/LICENSE
swcolorpicker-1.4.3.dist-info/METADATA
swcolorpicker-1.4.3.dist-info/WHEEL
swcolorpicker-1.4.3.dist-info/top_level.txt
swcolorpicker-1.4.3.dist-info/RECORD
