Metadata-Version: 2.1
Name: swcolorpicker
Version: 1.4.3
Summary: Color picker component of smartwheel-core
Home-page: https://github.com/enaix/smartwheel-colorpicker
Author: enaix
Author-email: eanix@protonmail.com
License: MIT
Keywords: python,color,gui,colorpicker,visual
Classifier: Programming Language :: Python :: 3
Classifier: Programming Language :: Python :: 3.7
Classifier: Programming Language :: Python :: 3.8
Classifier: Programming Language :: Python :: 3.9
Classifier: Programming Language :: Python :: 3.10
License-File: LICENSE
Requires-Dist: pyqt6
